Workbook

Sheet Loan_Calculator
A1: Loan EMI & Amortization Calculator
A3: Loan Inputs
A4: Loan Amount (₹) | B4: 2500000
A5: Annual Interest Rate (%) | B5: 0.085
A6: Loan Tenure (Years) | B6: 20
A7: Loan Start Date | B7: 46235
A9: Calculated Results
A10: Monthly Interest Rate | C10: =$B$5/12 -> 0.0070833333
A11: Total No. of Payments (Months) | C11: =$B$6*12 -> 240
A12: Monthly EMI (₹) | C12: =-PMT($C$10,$C$11,$B$4) -> 21695.581
A13: Total Amount Payable (₹) | C13: =$C$12*$C$11 -> 5206939.4
A14: Total Interest Payable (₹) | C14: =C13-B4 -> 2706939.4
A15: Interest as % of Loan Amount | C15: =C14/B4 -> 1.0827758

Sheet Amortization_Schedule
A1: Month-by-Month Amortization Schedule
A3: Month # | B3: Payment Date | C3: Opening Balance (₹) | D3: EMI (₹) | E3: Principal (₹) | F3: Interest (₹) | G3: Closing Balance (₹)
A4: 1 | B4: =Loan_Calculator!$B$7 -> 46235 | C4: =Loan_Calculator!$B$4 -> 2500000 | D4: =IF(A4<=Loan_Calculator!$C$11,Loan_Calculator!$C$12,0) -> 21695.581 | E4: =IF(A4<=Loan_Calculator!$C$11,-PPMT(Loan_Calculator!$C$10,A4,Loan_Calculator!$C$11,Loan_Calculator!$B$4),0) -> 3987.2475 | F4: =IF(A4<=Loan_Calculator!$C$11,-IPMT(Loan_Calculator!$C$10,A4,Loan_Calculator!$C$11,Loan_Calculator!$B$4),0) -> 17708.333 | G4: =MAX(0,C4-E4) -> 2496012.8
A5: 2 | B5: =EDATE(B4,1) -> 46266 | C5: =G4 -> 2496012.8 | D5: =IF(A5<=Loan_Calculator!$C$11,Loan_Calculator!$C$12,0) -> 21695.581 | E5: =IF(A5<=Loan_Calculator!$C$11,-PPMT(Loan_Calculator!$C$10,A5,Loan_Calculator!$C$11,Loan_Calculator!$B$4),0) -> 4015.4905 | F5: =IF(A5<=Loan_Calculator!$C$11,-IPMT(Loan_Calculator!$C$10,A5,Loan_Calculator!$C$11,Loan_Calculator!$B$4),0) -> 17680.09 | G5: =MAX(0,C5-E5) -> 2491997.3
A6: 3 | B6: =EDATE(B5,1) -> 46296 | C6: =G5 -> 2491997.3 | D6: =IF(A6<=Loan_Calculator!$C$11,Loan_Calculator!$C$12,0) -> 21695.581 | E6: =IF(A6<=Loan_Calculator!$C$11,-PPMT(Loan_Calculator!$C$10,A6,Loan_Calculator!$C$11,Loan_Calculator!$B$4),0) -> 4043.9336 | F6: =IF(A6<=Loan_Calculator!$C$11,-IPMT(Loan_Calculator!$C$10,A6,Loan_Calculator!$C$11,Loan_Calculator!$B$4),0) -> 17651.647 | G6: =MAX(0,C6-E6) -> 2487953.3
A7: 4 | B7: =EDATE(B6,1) -> 46327 | C7: =G6 -> 2487953.3 | D7: =IF(A7<=Loan_Calculator!$C$11,Loan_Calculator!$C$12,0) -> 21695.581 | E7: =IF(A7<=Loan_Calculator!$C$11,-PPMT(Loan_Calculator!$C$10,A7,Loan_Calculator!$C$11,Loan_Calculator!$B$4),0) -> 4072.5781 | F7: =IF(A7<=Loan_Calculator!$C$11,-IPMT(Loan_Calculator!$C$10,A7,Loan_Calculator!$C$11,Loan_Calculator!$B$4),0) -> 17623.003 | G7: =MAX(0,C7-E7) -> 2483880.8
A8: 5 | B8: =EDATE(B7,1) -> 46357 | C8: =G7 -> 2483880.8 | D8: =IF(A8<=Loan_Calculator!$C$11,Loan_Calculator!$C$12,0) -> 21695.581 | E8: =IF(A8<=Loan_Calculator!$C$11,-PPMT(Loan_Calculator!$C$10,A8,Loan_Calculator!$C$11,Loan_Calculator!$B$4),0) -> 4101.4255 | F8: =IF(A8<=Loan_Calculator!$C$11,-IPMT(Loan_Calculator!$C$10,A8,Loan_Calculator!$C$11,Loan_Calculator!$B$4),0) -> 17594.155 | G8: =MAX(0,C8-E8) -> 2479779.3
A9: 6 | B9: =EDATE(B8,1) -> 46388 | C9: =G8 -> 2479779.3 | D9: =IF(A9<=Loan_Calculator!$C$11,Loan_Calculator!$C$12,0) -> 21695.581 | E9: =IF(A9<=Loan_Calculator!$C$11,-PPMT(Loan_Calculator!$C$10,A9,Loan_Calculator!$C$11,Loan_Calculator!$B$4),0) -> 4130.4773 | F9: =IF(A9<=Loan_Calculator!$C$11,-IPMT(Loan_Calculator!$C$10,A9,Loan_Calculator!$C$11,Loan_Calculator!$B$4),0) -> 17565.104 | G9: =MAX(0,C9-E9) -> 2475648.8
A10: 7 | B10: =EDATE(B9,1) -> 46419 | C10: =G9 -> 2475648.8 | D10: =IF(A10<=Loan_Calculator!$C$11,Loan_Calculator!$C$12,0) -> 21695.581 | E10: =IF(A10<=Loan_Calculator!$C$11,-PPMT(Loan_Calculator!$C$10,A10,Loan_Calculator!$C$11,Loan_Calculator!$B$4),0) -> 4159.7348 | F10: =IF(A10<=Loan_Calculator!$C$11,-IPMT(Loan_Calculator!$C$10,A10,Loan_Calculator!$C$11,Loan_Calculator!$B$4),0) -> 17535.846 | G10: =MAX(0,C10-E10) -> 2471489.1
A11: 8 | B11: =EDATE(B10,1) -> 46447 | C11: =G10 -> 2471489.1 | D11: =IF(A11<=Loan_Calculator!$C$11,Loan_Calculator!$C$12,0) -> 21695.581 | E11: =IF(A11<=Loan_Calculator!$C$11,-PPMT(Loan_Calculator!$C$10,A11,Loan_Calculator!$C$11,Loan_Calculator!$B$4),0) -> 4189.1996 | F11: =IF(A11<=Loan_Calculator!$C$11,-IPMT(Loan_Calculator!$C$10,A11,Loan_Calculator!$C$11,Loan_Calculator!$B$4),0) -> 17506.381 | G11: =MAX(0,C11-E11) -> 2467299.9
A12: 9 | B12: =EDATE(B11,1) -> 46478 | C12: =G11 -> 2467299.9 | D12: =IF(A12<=Loan_Calculator!$C$11,Loan_Calculator!$C$12,0) -> 21695.581 | E12: =IF(A12<=Loan_Calculator!$C$11,-PPMT(Loan_Calculator!$C$10,A12,Loan_Calculator!$C$11,Loan_Calculator!$B$4),0) -> 4218.8731 | F12: =IF(A12<=Loan_Calculator!$C$11,-IPMT(Loan_Calculator!$C$10,A12,Loan_Calculator!$C$11,Loan_Calculator!$B$4),0) -> 17476.708 | G12: =MAX(0,C12-E12) -> 2463081
A13: 10 | B13: =EDATE(B12,1) -> 46508 | C13: =G12 -> 2463081 | D13: =IF(A13<=Loan_Calculator!$C$11,Loan_Calculator!$C$12,0) -> 21695.581 | E13: =IF(A13<=Loan_Calculator!$C$11,-PPMT(Loan_Calculator!$C$10,A13,Loan_Calculator!$C$11,Loan_Calculator!$B$4),0) -> 4248.7568 | F13: =IF(A13<=Loan_Calculator!$C$11,-IPMT(Loan_Calculator!$C$10,A13,Loan_Calculator!$C$11,Loan_Calculator!$B$4),0) -> 17446.824 | G13: =MAX(0,C13-E13) -> 2458832.3
A14: 11 | B14: =EDATE(B13,1) -> 46539 | C14: =G13 -> 2458832.3 | D14: =IF(A14<=Loan_Calculator!$C$11,Loan_Calculator!$C$12,0) -> 21695.581 | E14: =IF(A14<=Loan_Calculator!$C$11,-PPMT(Loan_Calculator!$C$10,A14,Loan_Calculator!$C$11,Loan_Calculator!$B$4),0) -> 4278.8522 | F14: =IF(A14<=Loan_Calculator!$C$11,-IPMT(Loan_Calculator!$C$10,A14,Loan_Calculator!$C$11,Loan_Calculator!$B$4),0) -> 17416.729 | G14: =MAX(0,C14-E14) -> 2454553.4
A15: 12 | B15: =EDATE(B14,1) -> 46569 | C15: =G14 -> 2454553.4 | D15: =IF(A15<=Loan_Calculator!$C$11,Loan_Calculator!$C$12,0) -> 21695.581 | E15: =IF(A15<=Loan_Calculator!$C$11,-PPMT(Loan_Calculator!$C$10,A15,Loan_Calculator!$C$11,Loan_Calculator!$B$4),0) -> 4309.1607 | F15: =IF(A15<=Loan_Calculator!$C$11,-IPMT(Loan_Calculator!$C$10,A15,Loan_Calculator!$C$11,Loan_Calculator!$B$4),0) -> 17386.42 | G15: =MAX(0,C15-E15) -> 2450244.3
A16: 13 | B16: =EDATE(B15,1) -> 46600 | C16: =G15 -> 2450244.3 | D16: =IF(A16<=Loan_Calculator!$C$11,Loan_Calculator!$C$12,0) -> 21695.581 | E16: =IF(A16<=Loan_Calculator!$C$11,-PPMT(Loan_Calculator!$C$10,A16,Loan_Calculator!$C$11,Loan_Calculator!$B$4),0) -> 4339.6839 | F16: =IF(A16<=Loan_Calculator!$C$11,-IPMT(Loan_Calculator!$C$10,A16,Loan_Calculator!$C$11,Loan_Calculator!$B$4),0) -> 17355.897 | G16: =MAX(0,C16-E16) -> 2445904.6
... A243: 240 | B243: =EDATE(B242,1) -> 53509 | C243: =G242 -> 21542.985 | D243: =IF(A243<=Loan_Calculator!$C$11,Loan_Calculator!$C$12,0) -> 21695.581 | E243: =IF(A243<=Loan_Calculator!$C$11,-PPMT(Loan_Calculator!$C$10,A243,Loan_Calculator!$C$11,Loan_Calculator!$B$4),0) -> 21542.985 | F243: =IF(A243<=Loan_Calculator!$C$11,-IPMT(Loan_Calculator!$C$10,A243,Loan_Calculator!$C$11,Loan_Calculator!$B$4),0) -> 152.59614 | G243: =MAX(0,C243-E243) -> 0

Sheet Yearly_Summary
A1: Year-Wise Repayment Summary
A3: Loan Year | B3: Principal Paid (₹) | C3: Interest Paid (₹) | D3: Total Paid (₹) | E3: Year-End Balance (₹)
A4: 1 | B4: =SUMIFS(Amortization_Schedule!$E$4:$E$243,Amortization_Schedule!$A$4:$A$243,">="&1,Amortization_Schedule!$A$4:$A$243,"<="&12) -> 49755.73 | C4: =SUMIFS(Amortization_Schedule!$F$4:$F$243,Amortization_Schedule!$A$4:$A$243,">="&1,Amortization_Schedule!$A$4:$A$243,"<="&12) -> 210591.24 | D4: =B4+C4 -> 260346.97 | E4: =IFERROR(INDEX(Amortization_Schedule!$G$4:$G$243,12),0) -> 2450244.3
A5: 2 | B5: =SUMIFS(Amortization_Schedule!$E$4:$E$243,Amortization_Schedule!$A$4:$A$243,">="&13,Amortization_Schedule!$A$4:$A$243,"<="&24) -> 54153.684 | C5: =SUMIFS(Amortization_Schedule!$F$4:$F$243,Amortization_Schedule!$A$4:$A$243,">="&13,Amortization_Schedule!$A$4:$A$243,"<="&24) -> 206193.29 | D5: =B5+C5 -> 260346.97 | E5: =IFERROR(INDEX(Amortization_Schedule!$G$4:$G$243,24),0) -> 2396090.6
A6: 3 | B6: =SUMIFS(Amortization_Schedule!$E$4:$E$243,Amortization_Schedule!$A$4:$A$243,">="&25,Amortization_Schedule!$A$4:$A$243,"<="&36) -> 58940.377 | C6: =SUMIFS(Amortization_Schedule!$F$4:$F$243,Amortization_Schedule!$A$4:$A$243,">="&25,Amortization_Schedule!$A$4:$A$243,"<="&36) -> 201406.59 | D6: =B6+C6 -> 260346.97 | E6: =IFERROR(INDEX(Amortization_Schedule!$G$4:$G$243,36),0) -> 2337150.2
A7: 4 | B7: =SUMIFS(Amortization_Schedule!$E$4:$E$243,Amortization_Schedule!$A$4:$A$243,">="&37,Amortization_Schedule!$A$4:$A$243,"<="&48) -> 64150.17 | C7: =SUMIFS(Amortization_Schedule!$F$4:$F$243,Amortization_Schedule!$A$4:$A$243,">="&37,Amortization_Schedule!$A$4:$A$243,"<="&48) -> 196196.8 | D7: =B7+C7 -> 260346.97 | E7: =IFERROR(INDEX(Amortization_Schedule!$G$4:$G$243,48),0) -> 2273000
A8: 5 | B8: =SUMIFS(Amortization_Schedule!$E$4:$E$243,Amortization_Schedule!$A$4:$A$243,">="&49,Amortization_Schedule!$A$4:$A$243,"<="&60) -> 69820.462 | C8: =SUMIFS(Amortization_Schedule!$F$4:$F$243,Amortization_Schedule!$A$4:$A$243,">="&49,Amortization_Schedule!$A$4:$A$243,"<="&60) -> 190526.51 | D8: =B8+C8 -> 260346.97 | E8: =IFERROR(INDEX(Amortization_Schedule!$G$4:$G$243,60),0) -> 2203179.6
A9: 6 | B9: =SUMIFS(Amortization_Schedule!$E$4:$E$243,Amortization_Schedule!$A$4:$A$243,">="&61,Amortization_Schedule!$A$4:$A$243,"<="&72) -> 75991.956 | C9: =SUMIFS(Amortization_Schedule!$F$4:$F$243,Amortization_Schedule!$A$4:$A$243,">="&61,Amortization_Schedule!$A$4:$A$243,"<="&72) -> 184355.01 | D9: =B9+C9 -> 260346.97 | E9: =IFERROR(INDEX(Amortization_Schedule!$G$4:$G$243,72),0) -> 2127187.6
A10: 7 | B10: =SUMIFS(Amortization_Schedule!$E$4:$E$243,Amortization_Schedule!$A$4:$A$243,">="&73,Amortization_Schedule!$A$4:$A$243,"<="&84) -> 82708.954 | C10: =SUMIFS(Amortization_Schedule!$F$4:$F$243,Amortization_Schedule!$A$4:$A$243,">="&73,Amortization_Schedule!$A$4:$A$243,"<="&84) -> 177638.02 | D10: =B10+C10 -> 260346.97 | E10: =IFERROR(INDEX(Amortization_Schedule!$G$4:$G$243,84),0) -> 2044478.7
A11: 8 | B11: =SUMIFS(Amortization_Schedule!$E$4:$E$243,Amortization_Schedule!$A$4:$A$243,">="&85,Amortization_Schedule!$A$4:$A$243,"<="&96) -> 90019.673 | C11: =SUMIFS(Amortization_Schedule!$F$4:$F$243,Amortization_Schedule!$A$4:$A$243,">="&85,Amortization_Schedule!$A$4:$A$243,"<="&96) -> 170327.3 | D11: =B11+C11 -> 260346.97 | E11: =IFERROR(INDEX(Amortization_Schedule!$G$4:$G$243,96),0) -> 1954459
A12: 9 | B12: =SUMIFS(Amortization_Schedule!$E$4:$E$243,Amortization_Schedule!$A$4:$A$243,">="&97,Amortization_Schedule!$A$4:$A$243,"<="&108) -> 97976.593 | C12: =SUMIFS(Amortization_Schedule!$F$4:$F$243,Amortization_Schedule!$A$4:$A$243,">="&97,Amortization_Schedule!$A$4:$A$243,"<="&108) -> 162370.38 | D12: =B12+C12 -> 260346.97 | E12: =IFERROR(INDEX(Amortization_Schedule!$G$4:$G$243,108),0) -> 1856482.4
A13: 10 | B13: =SUMIFS(Amortization_Schedule!$E$4:$E$243,Amortization_Schedule!$A$4:$A$243,">="&109,Amortization_Schedule!$A$4:$A$243,"<="&120) -> 106636.83 | C13: =SUMIFS(Amortization_Schedule!$F$4:$F$243,Amortization_Schedule!$A$4:$A$243,">="&109,Amortization_Schedule!$A$4:$A$243,"<="&120) -> 153710.14 | D13: =B13+C13 -> 260346.97 | E13: =IFERROR(INDEX(Amortization_Schedule!$G$4:$G$243,120),0) -> 1749845.6
A14: 11 | B14: =SUMIFS(Amortization_Schedule!$E$4:$E$243,Amortization_Schedule!$A$4:$A$243,">="&121,Amortization_Schedule!$A$4:$A$243,"<="&132) -> 116062.56 | C14: =SUMIFS(Amortization_Schedule!$F$4:$F$243,Amortization_Schedule!$A$4:$A$243,">="&121,Amortization_Schedule!$A$4:$A$243,"<="&132) -> 144284.41 | D14: =B14+C14 -> 260346.97 | E14: =IFERROR(INDEX(Amortization_Schedule!$G$4:$G$243,132),0) -> 1633783
A15: 12 | B15: =SUMIFS(Amortization_Schedule!$E$4:$E$243,Amortization_Schedule!$A$4:$A$243,">="&133,Amortization_Schedule!$A$4:$A$243,"<="&144) -> 126321.43 | C15: =SUMIFS(Amortization_Schedule!$F$4:$F$243,Amortization_Schedule!$A$4:$A$243,">="&133,Amortization_Schedule!$A$4:$A$243,"<="&144) -> 134025.54 | D15: =B15+C15 -> 260346.97 | E15: =IFERROR(INDEX(Amortization_Schedule!$G$4:$G$243,144),0) -> 1507461.6
A16: 13 | B16: =SUMIFS(Amortization_Schedule!$E$4:$E$243,Amortization_Schedule!$A$4:$A$243,">="&145,Amortization_Schedule!$A$4:$A$243,"<="&156) -> 137487.1 | C16: =SUMIFS(Amortization_Schedule!$F$4:$F$243,Amortization_Schedule!$A$4:$A$243,">="&145,Amortization_Schedule!$A$4:$A$243,"<="&156) -> 122859.87 | D16: =B16+C16 -> 260346.97 | E16: =IFERROR(INDEX(Amortization_Schedule!$G$4:$G$243,156),0) -> 1369974.5
A17: 14 | B17: =SUMIFS(Amortization_Schedule!$E$4:$E$243,Amortization_Schedule!$A$4:$A$243,">="&157,Amortization_Schedule!$A$4:$A$243,"<="&168) -> 149639.71 | C17: =SUMIFS(Amortization_Schedule!$F$4:$F$243,Amortization_Schedule!$A$4:$A$243,">="&157,Amortization_Schedule!$A$4:$A$243,"<="&168) -> 110707.26 | D17: =B17+C17 -> 260346.97 | E17: =IFERROR(INDEX(Amortization_Schedule!$G$4:$G$243,168),0) -> 1220334.8
A18: 15 | B18: =SUMIFS(Amortization_Schedule!$E$4:$E$243,Amortization_Schedule!$A$4:$A$243,">="&169,Amortization_Schedule!$A$4:$A$243,"<="&180) -> 162866.5 | C18: =SUMIFS(Amortization_Schedule!$F$4:$F$243,Amortization_Schedule!$A$4:$A$243,">="&169,Amortization_Schedule!$A$4:$A$243,"<="&180) -> 97480.471 | D18: =B18+C18 -> 260346.97 | E18: =IFERROR(INDEX(Amortization_Schedule!$G$4:$G$243,180),0) -> 1057468.3
A19: 16 | B19: =SUMIFS(Amortization_Schedule!$E$4:$E$243,Amortization_Schedule!$A$4:$A$243,">="&181,Amortization_Schedule!$A$4:$A$243,"<="&192) -> 177262.42 | C19: =SUMIFS(Amortization_Schedule!$F$4:$F$243,Amortization_Schedule!$A$4:$A$243,">="&181,Amortization_Schedule!$A$4:$A$243,"<="&192) -> 83084.554 | D19: =B19+C19 -> 260346.97 | E19: =IFERROR(INDEX(Amortization_Schedule!$G$4:$G$243,192),0) -> 880205.85
A20: 17 | B20: =SUMIFS(Amortization_Schedule!$E$4:$E$243,Amortization_Schedule!$A$4:$A$243,">="&193,Amortization_Schedule!$A$4:$A$243,"<="&204) -> 192930.8 | C20: =SUMIFS(Amortization_Schedule!$F$4:$F$243,Amortization_Schedule!$A$4:$A$243,">="&193,Amortization_Schedule!$A$4:$A$243,"<="&204) -> 67416.168 | D20: =B20+C20 -> 260346.97 | E20: =IFERROR(INDEX(Amortization_Schedule!$G$4:$G$243,204),0) -> 687275.05
A21: 18 | B21: =SUMIFS(Amortization_Schedule!$E$4:$E$243,Amortization_Schedule!$A$4:$A$243,">="&205,Amortization_Schedule!$A$4:$A$243,"<="&216) -> 209984.13 | C21: =SUMIFS(Amortization_Schedule!$F$4:$F$243,Amortization_Schedule!$A$4:$A$243,">="&205,Amortization_Schedule!$A$4:$A$243,"<="&216) -> 50362.84 | D21: =B21+C21 -> 260346.97 | E21: =IFERROR(INDEX(Amortization_Schedule!$G$4:$G$243,216),0) -> 477290.92
A22: 19 | B22: =SUMIFS(Amortization_Schedule!$E$4:$E$243,Amortization_Schedule!$A$4:$A$243,">="&217,Amortization_Schedule!$A$4:$A$243,"<="&228) -> 228544.82 | C22: =SUMIFS(Amortization_Schedule!$F$4:$F$243,Amortization_Schedule!$A$4:$A$243,">="&217,Amortization_Schedule!$A$4:$A$243,"<="&228) -> 31802.152 | D22: =B22+C22 -> 260346.97 | E22: =IFERROR(INDEX(Amortization_Schedule!$G$4:$G$243,228),0) -> 248746.1
A23: 20 | B23: =SUMIFS(Amortization_Schedule!$E$4:$E$243,Amortization_Schedule!$A$4:$A$243,">="&229,Amortization_Schedule!$A$4:$A$243,"<="&240) -> 248746.1 | C23: =SUMIFS(Amortization_Schedule!$F$4:$F$243,Amortization_Schedule!$A$4:$A$243,">="&229,Amortization_Schedule!$A$4:$A$243,"<="&240) -> 11600.869 | D23: =B23+C23 -> 260346.97 | E23: =IFERROR(INDEX(Amortization_Schedule!$G$4:$G$243,240),0) -> 0

Sheet EMI_Sensitivity
A1: EMI Sensitivity Grid — Interest Rate vs Tenure
A3: Rate ↓ / Tenure (Yrs) → | B3: 10 | C3: 15 | D3: 20 | E3: 25 | F3: 30
A4: 0.075 | B4: =-PMT($A4/12,10*12,Loan_Calculator!$B$4) -> 29675.442 | C4: =-PMT($A4/12,15*12,Loan_Calculator!$B$4) -> 23175.309 | D4: =-PMT($A4/12,20*12,Loan_Calculator!$B$4) -> 20139.83 | E4: =-PMT($A4/12,25*12,Loan_Calculator!$B$4) -> 18474.779 | F4: =-PMT($A4/12,30*12,Loan_Calculator!$B$4) -> 17480.363
A5: 0.08 | B5: =-PMT($A5/12,10*12,Loan_Calculator!$B$4) -> 30331.899 | C5: =-PMT($A5/12,15*12,Loan_Calculator!$B$4) -> 23891.302 | D5: =-PMT($A5/12,20*12,Loan_Calculator!$B$4) -> 20911.002 | E5: =-PMT($A5/12,25*12,Loan_Calculator!$B$4) -> 19295.405 | F5: =-PMT($A5/12,30*12,Loan_Calculator!$B$4) -> 18344.114
A6: 0.085 | B6: =-PMT($A6/12,10*12,Loan_Calculator!$B$4) -> 30996.422 | C6: =-PMT($A6/12,15*12,Loan_Calculator!$B$4) -> 24618.489 | D6: =-PMT($A6/12,20*12,Loan_Calculator!$B$4) -> 21695.581 | E6: =-PMT($A6/12,25*12,Loan_Calculator!$B$4) -> 20130.677 | F6: =-PMT($A6/12,30*12,Loan_Calculator!$B$4) -> 19222.837
A7: 0.09 | B7: =-PMT($A7/12,10*12,Loan_Calculator!$B$4) -> 31668.943 | C7: =-PMT($A7/12,15*12,Loan_Calculator!$B$4) -> 25356.665 | D7: =-PMT($A7/12,20*12,Loan_Calculator!$B$4) -> 22493.149 | E7: =-PMT($A7/12,25*12,Loan_Calculator!$B$4) -> 20979.909 | F7: =-PMT($A7/12,30*12,Loan_Calculator!$B$4) -> 20115.565
A8: 0.095 | B8: =-PMT($A8/12,10*12,Loan_Calculator!$B$4) -> 32349.389 | C8: =-PMT($A8/12,15*12,Loan_Calculator!$B$4) -> 26105.617 | D8: =-PMT($A8/12,20*12,Loan_Calculator!$B$4) -> 23303.28 | E8: =-PMT($A8/12,25*12,Loan_Calculator!$B$4) -> 21842.417 | F8: =-PMT($A8/12,30*12,Loan_Calculator!$B$4) -> 21021.355
A9: 0.1 | B9: =-PMT($A9/12,10*12,Loan_Calculator!$B$4) -> 33037.684 | C9: =-PMT($A9/12,15*12,Loan_Calculator!$B$4) -> 26865.128 | D9: =-PMT($A9/12,20*12,Loan_Calculator!$B$4) -> 24125.541 | E9: =-PMT($A9/12,25*12,Loan_Calculator!$B$4) -> 22717.519 | F9: =-PMT($A9/12,30*12,Loan_Calculator!$B$4) -> 21939.289
